pokemaster/__init__.py
pokemaster/__version__.py
pokemaster/_database.py
pokemaster/game_version.py
pokemaster/pokemon.py
pokemaster/prng.py
pokemaster/stats.py
pokemaster/weather.py
pokemaster-0.2.2.dist-info/WHEEL
pokemaster-0.2.2.dist-info/METADATA
pokemaster-0.2.2.dist-info/RECORD
